FragStatsPy/__init__.py
FragStatsPy/__main__.py
FragStatsPy/frag_model.py
FragStatsPy-0.0.2.dist-info/LICENSE
FragStatsPy-0.0.2.dist-info/METADATA
FragStatsPy-0.0.2.dist-info/WHEEL
FragStatsPy-0.0.2.dist-info/top_level.txt
FragStatsPy-0.0.2.dist-info/RECORD
