Metadata-Version: 2.1
Name: FragStatsPy
Version: 0.0.2
Summary: A Python wrapper for Fragstats.
Author-email: Scott Lawson <scott.lawson@uvm.edu>
License: MIT License
Project-URL: Homepage, https://github.com/sclaw/FragStatsPy
Keywords: Landsacape metrics,spatial statistics,fragstats
Classifier: License :: OSI Approved :: MIT License
Classifier: Programming Language :: Python
Classifier: Programming Language :: Python :: 3
Requires-Python: >=3.9
License-File: LICENSE
Requires-Dist: pandas
Provides-Extra: dev
Requires-Dist: gdal ; extra == 'dev'
